{"Api.tag":"null/状态规则值","getById":{},"deleteById":{"ApiOperation.value":"删除状态规则值","ApiImplicitParam.AssetStatusRuleVVOMeta.ID.name":"主键"},"save":{"ApiImplicitParam.AssetStatusRuleVVOMeta.OPER_CODE.name":"操作编码","ApiImplicitParam.AssetStatusRuleVVOMeta.STATUS_CODE.name":"状态编码","ApiOperation.value":"保存状态规则值","ApiImplicitParam.AssetStatusRuleVVOMeta.ID.name":"主键"},"insert":{"ApiImplicitParam.AssetStatusRuleVVOMeta.OPER_CODE.name":"操作编码","ApiImplicitParam.AssetStatusRuleVVOMeta.STATUS_CODE.name":"状态编码","ApiOperation.value":"添加状态规则值","ApiImplicitParam.AssetStatusRuleVVOMeta.ID.name":"主键"},"update":{"ApiImplicitParam.AssetStatusRuleVVOMeta.OPER_CODE.name":"操作编码","ApiImplicitParam.AssetStatusRuleVVOMeta.STATUS_CODE.name":"状态编码","ApiOperation.value":"更新状态规则值","ApiImplicitParam.AssetStatusRuleVVOMeta.ID.name":"主键"},"queryPagedList":{"ApiImplicitParam.AssetStatusRuleVVOMeta.OPER_CODE.name":"操作编码","ApiImplicitParam.AssetStatusRuleVVOMeta.STATUS_CODE.name":"状态编码","ApiOperation.value":"分页查询状态规则值","ApiImplicitParam.AssetStatusRuleVVOMeta.ID.name":"主键"},"queryList":{"ApiImplicitParam.AssetStatusRuleVVOMeta.OPER_CODE.name":"操作编码","ApiImplicitParam.AssetStatusRuleVVOMeta.STATUS_CODE.name":"状态编码","ApiOperation.value":"查询状态规则值","ApiImplicitParam.AssetStatusRuleVVOMeta.ID.name":"主键"}}