{"Api.tag":"null/配置库","getById":{"ApiImplicitParam.CmdbModelVOMeta.ID.name":"主键"},"deleteById":{"ApiOperation.value":"删除配置库","ApiImplicitParam.CmdbModelVOMeta.ID.name":"主键"},"save":{"ApiImplicitParam.CmdbModelVOMeta.SORT.name":"排序","ApiOperation.value":"保存配置库","ApiImplicitParam.CmdbModelVOMeta.ID.name":"主键","ApiImplicitParam.CmdbModelVOMeta.CODE.name":"编码","ApiImplicitParam.CmdbModelVOMeta.HIERARCHY_NAME.name":"节点路径名称","ApiImplicitParam.CmdbModelVOMeta.SOURCE_TYPE.name":"数据来源","ApiImplicitParam.CmdbModelVOMeta.NAME.name":"名称","ApiImplicitParam.CmdbModelVOMeta.FULL_NAME.name":"全称","ApiImplicitParam.CmdbModelVOMeta.STORAGE_TYPE.name":"存储方式","ApiImplicitParam.CmdbModelVOMeta.MODEL_TYPE.name":"模型类型","ApiImplicitParam.CmdbModelVOMeta.DATA_SOURCE.name":"来源方式","ApiImplicitParam.CmdbModelVOMeta.SOURCE.name":"来源","ApiImplicitParam.CmdbModelVOMeta.NOTES.name":"备注","ApiImplicitParam.CmdbModelVOMeta.PARENT_ID.name":"父节点","ApiImplicitParam.CmdbModelVOMeta.HIERARCHY.name":"节点路径","ApiImplicitParam.CmdbModelVOMeta.STATUS.name":"状态"},"insert":{"ApiImplicitParam.CmdbModelVOMeta.SORT.name":"排序","ApiOperation.value":"添加配置库","ApiImplicitParam.CmdbModelVOMeta.ID.name":"主键","ApiImplicitParam.CmdbModelVOMeta.CODE.name":"编码","ApiImplicitParam.CmdbModelVOMeta.HIERARCHY_NAME.name":"节点路径名称","ApiImplicitParam.CmdbModelVOMeta.SOURCE_TYPE.name":"数据来源","ApiImplicitParam.CmdbModelVOMeta.NAME.name":"名称","ApiImplicitParam.CmdbModelVOMeta.FULL_NAME.name":"全称","ApiImplicitParam.CmdbModelVOMeta.STORAGE_TYPE.name":"存储方式","ApiImplicitParam.CmdbModelVOMeta.MODEL_TYPE.name":"模型类型","ApiImplicitParam.CmdbModelVOMeta.DATA_SOURCE.name":"来源方式","ApiImplicitParam.CmdbModelVOMeta.SOURCE.name":"来源","ApiImplicitParam.CmdbModelVOMeta.NOTES.name":"备注","ApiImplicitParam.CmdbModelVOMeta.PARENT_ID.name":"父节点","ApiImplicitParam.CmdbModelVOMeta.HIERARCHY.name":"节点路径","ApiImplicitParam.CmdbModelVOMeta.STATUS.name":"状态"},"update":{"ApiImplicitParam.CmdbModelVOMeta.SORT.name":"排序","ApiOperation.value":"更新配置库","ApiImplicitParam.CmdbModelVOMeta.ID.name":"主键","ApiImplicitParam.CmdbModelVOMeta.CODE.name":"编码","ApiImplicitParam.CmdbModelVOMeta.HIERARCHY_NAME.name":"节点路径名称","ApiImplicitParam.CmdbModelVOMeta.SOURCE_TYPE.name":"数据来源","ApiImplicitParam.CmdbModelVOMeta.NAME.name":"名称","ApiImplicitParam.CmdbModelVOMeta.FULL_NAME.name":"全称","ApiImplicitParam.CmdbModelVOMeta.STORAGE_TYPE.name":"存储方式","ApiImplicitParam.CmdbModelVOMeta.MODEL_TYPE.name":"模型类型","ApiImplicitParam.CmdbModelVOMeta.DATA_SOURCE.name":"来源方式","ApiImplicitParam.CmdbModelVOMeta.SOURCE.name":"来源","ApiImplicitParam.CmdbModelVOMeta.NOTES.name":"备注","ApiImplicitParam.CmdbModelVOMeta.PARENT_ID.name":"父节点","ApiImplicitParam.CmdbModelVOMeta.HIERARCHY.name":"节点路径","ApiImplicitParam.CmdbModelVOMeta.STATUS.name":"状态"},"queryPagedList":{"ApiImplicitParam.CmdbModelVOMeta.SORT.name":"排序","ApiOperation.value":"分页查询配置库","ApiImplicitParam.CmdbModelVOMeta.ID.name":"主键","ApiImplicitParam.CmdbModelVOMeta.CODE.name":"编码","ApiImplicitParam.CmdbModelVOMeta.HIERARCHY_NAME.name":"节点路径名称","ApiImplicitParam.CmdbModelVOMeta.SOURCE_TYPE.name":"数据来源","ApiImplicitParam.CmdbModelVOMeta.NAME.name":"名称","ApiImplicitParam.CmdbModelVOMeta.FULL_NAME.name":"全称","ApiImplicitParam.CmdbModelVOMeta.STORAGE_TYPE.name":"存储方式","ApiImplicitParam.CmdbModelVOMeta.MODEL_TYPE.name":"模型类型","ApiImplicitParam.CmdbModelVOMeta.DATA_SOURCE.name":"来源方式","ApiImplicitParam.CmdbModelVOMeta.SOURCE.name":"来源","ApiImplicitParam.CmdbModelVOMeta.NOTES.name":"备注","ApiImplicitParam.CmdbModelVOMeta.PARENT_ID.name":"父节点","ApiImplicitParam.CmdbModelVOMeta.HIERARCHY.name":"节点路径","ApiImplicitParam.CmdbModelVOMeta.STATUS.name":"状态"},"queryList":{"ApiImplicitParam.CmdbModelVOMeta.SORT.name":"排序","ApiOperation.value":"查询配置库","ApiImplicitParam.CmdbModelVOMeta.ID.name":"主键","ApiImplicitParam.CmdbModelVOMeta.CODE.name":"编码","ApiImplicitParam.CmdbModelVOMeta.HIERARCHY_NAME.name":"节点路径名称","ApiImplicitParam.CmdbModelVOMeta.SOURCE_TYPE.name":"数据来源","ApiImplicitParam.CmdbModelVOMeta.NAME.name":"名称","ApiImplicitParam.CmdbModelVOMeta.FULL_NAME.name":"全称","ApiImplicitParam.CmdbModelVOMeta.STORAGE_TYPE.name":"存储方式","ApiImplicitParam.CmdbModelVOMeta.MODEL_TYPE.name":"模型类型","ApiImplicitParam.CmdbModelVOMeta.DATA_SOURCE.name":"来源方式","ApiImplicitParam.CmdbModelVOMeta.SOURCE.name":"来源","ApiImplicitParam.CmdbModelVOMeta.NOTES.name":"备注","ApiImplicitParam.CmdbModelVOMeta.PARENT_ID.name":"父节点","ApiImplicitParam.CmdbModelVOMeta.HIERARCHY.name":"节点路径","ApiImplicitParam.CmdbModelVOMeta.STATUS.name":"状态"}}